vunghixuan_package/__init__.py
vunghixuan_package/api_and_otp.py
vunghixuan_package/create_project.py
vunghixuan_package/main.py
vunghixuan_package-0.1.0.dist-info/METADATA
vunghixuan_package-0.1.0.dist-info/WHEEL
vunghixuan_package-0.1.0.dist-info/entry_points.txt
vunghixuan_package-0.1.0.dist-info/top_level.txt
vunghixuan_package-0.1.0.dist-info/RECORD
